afxano_keras/__init__.py
afxano_keras/activations.py
afxano_keras/layers.py
afxano_keras/metrics.py
afxano_keras/models.py
afxano_keras-0.2.0.dist-info/LICENSE
afxano_keras-0.2.0.dist-info/METADATA
afxano_keras-0.2.0.dist-info/WHEEL
afxano_keras-0.2.0.dist-info/top_level.txt
afxano_keras-0.2.0.dist-info/RECORD
