Metadata-Version: 2.1
Name: afxano-keras
Version: 0.2.0
Summary: A small package of extensions for keras
Home-page: https://github.com/jaypmorgan/afxano-keras
Author: Jay Morgan
Author-email: jay@morganwastaken.com
Requires-Python: >=3.6
License-File: LICENSE
Requires-Dist: keras (==2.*)
Requires-Dist: tensorflow (==2.*)
